topsis_manav_102303990/__init__.py
topsis_manav_102303990/topsis.py
topsis_manav_102303990-1.0.2.dist-info/METADATA
topsis_manav_102303990-1.0.2.dist-info/WHEEL
topsis_manav_102303990-1.0.2.dist-info/entry_points.txt
topsis_manav_102303990-1.0.2.dist-info/top_level.txt
topsis_manav_102303990-1.0.2.dist-info/RECORD
