Metadata-Version: 2.1
Name: topsis-manav-102303990
Version: 1.0.2
Summary: A Python package for TOPSIS method
Home-page: UNKNOWN
Author: Manav Bhullar
Author-email: manavbhullar341@gmail.com
License: UNKNOWN
Platform: UNKNOWN
Requires-Python: >=3.7
Requires-Dist: pandas
Requires-Dist: numpy
